{"cameraMode":{"drawMode":0,"name":"Shaded","section":"Shading Mode"},"sceneLighting":false,"audioPlay":false,"sceneViewState":{"showFog":true,"showMaterialUpdate":false,"showSkybox":false,"showFlares":true,"showImageEffects":true,"showParticleSystems":true},"in2DMode":false,"pivot":{"x":-15.273722648620606,"y":6.375185489654541,"z":24.308502197265626},"rotation":{"x":0.07924342155456543,"y":0.7618713974952698,"z":-0.09604164212942124,"w":0.6359255313873291},"size":18.24754524230957,"orthographic":false}